{
	"name": "Ubuntu 22.04",
	
	
	"build": {
			// Path is relative to the devcontainer.json file.
			"dockerfile": "Dockerfile"
			},

  	"features": {
    		
  				},


	"mounts": [
		
	],
	"customizations": {
		"vscode": {
			"settings": {
			
			},
			"extensions": [
				"ms-vscode.cpptools"
			]
		},
		"codespaces": {
			"settings": {
			
			},
			"extensions": [
				"ms-vscode.cpptools"
			]
		}
	},
	
	"runArgs": ["--privileged"],


	// More info: https://aka.ms/dev-containers-non-root.
	 "remoteUser": "vscode"
}